drm_api/Access.py
drm_api/Api.py
drm_api/Client.py
drm_api/__init__.py
oracle_drm_api-0.2.0.dist-info/METADATA
oracle_drm_api-0.2.0.dist-info/RECORD
oracle_drm_api-0.2.0.dist-info/WHEEL
oracle_drm_api-0.2.0.dist-info/top_level.txt
