Metadata-Version: 2.1
Name: oracle-drm-api
Version: 0.2.0
Summary: Oracle Data Relationship Management API Client
Home-page: https://github.com/tevpro/drm_api
Author: Keith Kikta
Author-email: keith.kikta@tevpro.com
License: UNKNOWN
Platform: UNKNOWN
Classifier: Programming Language :: Python :: 3
Classifier: License :: OSI Approved :: MIT License
Classifier: Operating System :: OS Independent
Requires-Dist: zeep (>=2.5.0)
